arcbound/__init__.py
arcbound/arc.py
arcbound/graph.py
arcbound/release.py
arcbound/requires.py
arcbound/visualize.py
arcbound-0.0.5.dist-info/LICENSE
arcbound-0.0.5.dist-info/METADATA
arcbound-0.0.5.dist-info/WHEEL
arcbound-0.0.5.dist-info/top_level.txt
arcbound-0.0.5.dist-info/RECORD
