Metadata-Version: 2.1
Name: arcbound
Version: 0.0.5
Summary: Collection of tools to arrange bound methods into a graph.
Home-page: https://github.com/JHwangAstro/arcbound
Author: Jason Hwang
Author-email: jhwang.astro@gmail.com
License: UNKNOWN
Platform: UNKNOWN
Classifier: Programming Language :: Python :: 3
Classifier: License :: OSI Approved :: GNU General Public License v3 (GPLv3)
Classifier: Operating System :: OS Independent
Requires-Python: >=3.6
Requires-Dist: attrs (>=19.3.0)
Provides-Extra: graphviz
Requires-Dist: graphviz (==0.13.2) ; extra == 'graphviz'
